drf_serialization_magic/__init__.py
drf_serialization_magic/core.py
drf_serialization_magic/models.py
drf_serialization_magic/serializers.py
drf_serialization_magic-1.0.4.dist-info/LICENSE
drf_serialization_magic-1.0.4.dist-info/METADATA
drf_serialization_magic-1.0.4.dist-info/WHEEL
drf_serialization_magic-1.0.4.dist-info/top_level.txt
drf_serialization_magic-1.0.4.dist-info/RECORD
