Metadata-Version: 2.1
Name: drf-serialization-magic
Version: 1.0.4
Summary: Open library for Django Rest Framework to reduce the duplication of code when working with Serializer
Home-page: https://github.com/tkppro/drf-serialization-magic
Author: Thang Dang Minh
Author-email: thangdangdev@gmail.com
License: BSD
Classifier: Development Status :: 5 - Production/Stable
Classifier: Environment :: Web Environment
Classifier: Framework :: Django
Classifier: Intended Audience :: Developers
Classifier: License :: OSI Approved :: BSD License
Classifier: Operating System :: OS Independent
Classifier: Natural Language :: English
Classifier: Programming Language :: Python :: 3
Classifier: Programming Language :: Python :: 3.6
Classifier: Programming Language :: Python :: 3.7
Classifier: Programming Language :: Python :: 3.8
Classifier: Topic :: Internet :: WWW/HTTP
Requires-Python: >=3.7
License-File: LICENSE
Requires-Dist: Django (>=3.0)
